{
  "project_info": {
    "project_number": "548465772262",
    "project_id": "lavie-53aea",
    "storage_bucket": "lavie-53aea.appspot.com"
  },
  "client": [
    {
      "client_info": {
        "mobilesdk_app_id": "1:548465772262:android:5e3940c7aa956313329d27",
        "android_client_info": {
          "package_name": "com.example.life"
        }
      },
      "oauth_client": [
        {
          "client_id": "548465772262-riatnvh9s58ftvf4lj8585bp6knbmcqk.apps.googleusercontent.com",
          "client_type": 3
        }
      ],
      "api_key": [
        {
          "current_key": "AIzaSyAF35XIMEQx6jgimd2Bhmhmt2M_q7F0ztQ"
        }
      ],
      "services": {
        "appinvite_service": {
          "other_platform_oauth_client": [
            {
              "client_id": "548465772262-riatnvh9s58ftvf4lj8585bp6knbmcqk.apps.googleusercontent.com",
              "client_type": 3
            }
          ]
        }
      }
    }
  ],
  "configuration_version": "1"
}